CHANGES.txt
README.txt
bootstrap.py
buildout.cfg
setup.py
src/z3c/__init__.py
src/z3c.iplocation.egg-info/PKG-INFO
src/z3c.iplocation.egg-info/SOURCES.txt
src/z3c.iplocation.egg-info/dependency_links.txt
src/z3c.iplocation.egg-info/namespace_packages.txt
src/z3c.iplocation.egg-info/not-zip-safe
src/z3c.iplocation.egg-info/requires.txt
src/z3c.iplocation.egg-info/top_level.txt
src/z3c/iplocation/README.txt
src/z3c/iplocation/__init__.py
src/z3c/iplocation/interfaces.py
src/z3c/iplocation/ipligence-basic-demo.txt
src/z3c/iplocation/ipligence-lite-demo.txt
src/z3c/iplocation/ipligence-max-demo.txt
src/z3c/iplocation/ipligence.py
src/z3c/iplocation/locator.py
src/z3c/iplocation/tests.py