Metadata-Version: 1.0
Name: z3c.iplocation
Version: 0.5.0
Summary: Geo location utility for Zope3
Home-page: http://pypi.python.org/pypi/z3c.iplocation
Author: Roger Ineichen, Stephan Richter and the Zope Community
Author-email: zope-dev@zope.org
License: ZPL 2.1
Keywords: zope3 z3c geolocation ipligence iplocation
Platform: UNKNOWN
Classifier: Development Status :: 4 - Beta
Classifier: Environment :: Web Environment
Classifier: Intended Audience :: Developers
Classifier: License :: OSI Approved :: Zope Public License
Classifier: Programming Language :: Python
Classifier: Natural Language :: English
Classifier: Operating System :: OS Independent
Classifier: Topic :: Internet :: WWW/HTTP
Classifier: Framework :: Zope3
